pupil_labs/lsl_relay/__init__.py
pupil_labs/lsl_relay/__main__.py
pupil_labs/lsl_relay/channels.py
pupil_labs/lsl_relay/cli.py
pupil_labs/lsl_relay/linear_time_model.py
pupil_labs/lsl_relay/outlets.py
pupil_labs/lsl_relay/relay.py
pupil_labs/lsl_relay/xdf_cloud_time_sync.py
lsl_relay-3.2.3.dist-info/LICENSE
lsl_relay-3.2.3.dist-info/METADATA
lsl_relay-3.2.3.dist-info/WHEEL
lsl_relay-3.2.3.dist-info/entry_points.txt
lsl_relay-3.2.3.dist-info/top_level.txt
lsl_relay-3.2.3.dist-info/RECORD
